genai_textkit/__init__.py
genai_textkit/config.py
genai_textkit/text.py
genai_textkit-0.1.8.dist-info/METADATA
genai_textkit-0.1.8.dist-info/WHEEL
genai_textkit-0.1.8.dist-info/top_level.txt
genai_textkit-0.1.8.dist-info/RECORD
