Metadata-Version: 2.4
Name: genai_textkit
Version: 0.1.8
Summary: A no-API-key, CPU-friendly GenAI library for text generation, summarization, sentiment classification, and translation.
License: MIT
Project-URL: Homepage, https://github.com/IamAbhinav01/GenAI
Project-URL: Documentation, https://github.com/IamAbhinav01/GenAI#readme
Project-URL: Repository, https://github.com/IamAbhinav01/GenAI
Requires-Python: >=3.10
Requires-Dist: accelerate>=1.9.0
Requires-Dist: transformers>=4.40.0
Requires-Dist: pytest
